main.py
jam_bank_system-0.1.0.dist-info/METADATA
jam_bank_system-0.1.0.dist-info/WHEEL
jam_bank_system-0.1.0.dist-info/entry_points.txt
jam_bank_system-0.1.0.dist-info/top_level.txt
jam_bank_system-0.1.0.dist-info/RECORD
